db_lonewolpy/__init__.py
db_lonewolpy/db.py
tests/__init__.py
tests/test_db.py
db_lonewolpy-1.0.15.dist-info/METADATA
db_lonewolpy-1.0.15.dist-info/WHEEL
db_lonewolpy-1.0.15.dist-info/top_level.txt
db_lonewolpy-1.0.15.dist-info/RECORD
