Metadata-Version: 2.1
Name: db-lonewolpy
Version: 1.0.15
Summary: DB Connector
Home-page: https://github.com/nikunjs21/db-lonewolpy
Author: Nikunj
Author-email: savaliyanikunj2@gmail.com
License: MIT
Requires-Dist: mysql-connector-python (==8.1.0)
